setup.py
bin/saucestorage
saucestorage/__init__.py
saucestorage/version.json
saucestorage.egg-info/PKG-INFO
saucestorage.egg-info/SOURCES.txt
saucestorage.egg-info/dependency_links.txt
saucestorage.egg-info/top_level.txt