Metadata-Version: 1.1
Name: saucestorage
Version: 0.3.1
Summary: Sauce Labs Storage API library and command-line tool
Home-page: https://github.com/saucelabs/saucestorage
Author: Sauce Labs
Author-email: dev@saucelabs.com
License: UNKNOWN
Keywords: saucelabs
Platform: UNKNOWN
Classifier: Development Status :: 3 - Alpha
Classifier: Intended Audience :: Developers
Classifier: Topic :: Utilities
Classifier: License :: OSI Approved :: Apache Software License
Classifier: Programming Language :: Python :: 2.7
